onnxllm/__init__.py
onnxllm/version.py
onnxllm/backends/__init__.py
onnxllm/backends/onnxruntime/__init__.py
onnxllm/backends/onnxruntime/backend.py
onnxllm/models/__init__.py
onnxllm/models/auto_config.py
onnxllm/models/auto_factory.py
onnxllm/models/auto_models.py
onnxllm/models/chatglm/__init__.py
onnxllm/models/chatglm/llm_chatglm.py
onnxllm/models/llama3/__init__.py
onnxllm/models/llama3/llm_llama3.py
onnxllm/models/qwen/__init__.py
onnxllm/models/qwen/llm_qwen.py
onnxllm-0.0.1.dist-info/LICENSE
onnxllm-0.0.1.dist-info/METADATA
onnxllm-0.0.1.dist-info/WHEEL
onnxllm-0.0.1.dist-info/top_level.txt
onnxllm-0.0.1.dist-info/zip-safe
onnxllm-0.0.1.dist-info/RECORD
